[{"id":"ma-2552292","label":"Ad Darwa","lat":33.37487,"lon":-7.5356,"type":"city"},{"id":"ma-2561737","label":"Afourer","lat":32.20721,"lon":-6.53824,"type":"city"},{"id":"ma-2561668","label":"Agadir","lat":30.42018,"lon":-9.59815,"type":"city"},{"id":"ma-2561539","label":"Agdz","lat":30.69356,"lon":-6.44628,"type":"city"},{"id":"ma-2557310","label":"Aghbala","lat":32.48076,"lon":-5.64295,"type":"city"},{"id":"ma-2561358","label":"Agourai","lat":33.63,"lon":-5.58,"type":"city"},{"id":"ma-2561290","label":"Aguelmous","lat":33.16139,"lon":-5.84626,"type":"city"},{"id":"ma-2561124","label":"Ahfir","lat":34.95368,"lon":-2.10027,"type":"city"},{"id":"ma-2560940","label":"Ain Aicha","lat":34.46103,"lon":-4.69026,"type":"city"},{"id":"ma-12718687","label":"Ain Attig","lat":33.88758,"lon":-6.96807,"type":"city"},{"id":"ma-2560922","label":"Ain Beni Mathar","lat":34.0097,"lon":-2.03238,"type":"city"},{"id":"ma-2560905","label":"Ain Cheggag","lat":33.89286,"lon":-5.03699,"type":"city"},{"id":"ma-2560939","label":"Ain El Aouda","lat":33.80333,"lon":-6.79461,"type":"city"},{"id":"ma-2560841","label":"Ain Harrouda","lat":33.63737,"lon":-7.44971,"type":"city"},{"id":"ma-10984425","label":"Ain Karma","lat":34.00664,"lon":-5.6157,"type":"city"},{"id":"ma-2560813","label":"Ain Leuh","lat":33.28984,"lon":-5.33863,"type":"city"},{"id":"ma-2560774","label":"Ain Taoujdat","lat":33.93575,"lon":-5.21328,"type":"city"},{"id":"ma-10374934","label":"Ait Melloul","lat":30.34164,"lon":-9.50356,"type":"city"},{"id":"ma-2540953","label":"Ait Ouaoumana","lat":32.71029,"lon":-5.8063,"type":"city"},{"id":"ma-2559217","label":"Ait Ourir","lat":31.56517,"lon":-7.66163,"type":"city"},{"id":"ma-2558844","label":"Ait Yazza","lat":30.50188,"lon":-8.79917,"type":"city"},{"id":"ma-2558766","label":"Ajdir","lat":35.19537,"lon":-3.91166,"type":"city"},{"id":"ma-2558667","label":"Akka","lat":29.38914,"lon":-8.2549,"type":"city"},{"id":"ma-2564788","label":"Aklim","lat":34.92,"lon":-2.43,"type":"city"},{"id":"ma-2542013","label":"Al Aaroui","lat":35.0109,"lon":-3.00938,"type":"city"},{"id":"ma-2550547","label":"Al Brouj","lat":32.50467,"lon":-7.19238,"type":"city"},{"id":"ma-2548830","label":"Al Fqih Ben Calah","lat":32.50213,"lon":-6.68771,"type":"city"},{"id":"ma-2558545","label":"Al Hoceima","lat":35.25165,"lon":-3.93723,"type":"city"},{"id":"ma-2558424","label":"Al M'aziz","lat":33.67073,"lon":-6.31613,"type":"city"},{"id":"ma-12718667","label":"Al Machouar - Stinia","lat":33.88543,"lon":-5.55574,"type":"city"},{"id":"ma-2550016","label":"Al Qbab","lat":32.74121,"lon":-5.51994,"type":"city"},{"id":"ma-2558414","label":"Almis du Guigou","lat":33.38738,"lon":-4.82927,"type":"city"},{"id":"ma-2558398","label":"Alnif","lat":31.11411,"lon":-5.17154,"type":"city"},{"id":"ma-2558052","label":"Amizmiz","lat":31.21673,"lon":-8.23184,"type":"city"},{"id":"ma-2557533","label":"Aoulouz","lat":30.67307,"lon":-8.18087,"type":"city"},{"id":"ma-2557500","label":"Aourir","lat":30.49238,"lon":-9.6355,"type":"city"},{"id":"ma-2463161","label":"Aousserd","lat":22.554,"lon":-14.33,"type":"city"},{"id":"ma-2557134","label":"Ar Rommani","lat":33.52838,"lon":-6.60348,"type":"city"},{"id":"ma-2550681","label":"Arbaa Laaounate","lat":32.7434,"lon":-8.19501,"type":"city"},{"id":"ma-2549356","label":"Arfoud","lat":31.4353,"lon":-4.23258,"type":"city"},{"id":"ma-2557055","label":"Asilah","lat":35.46522,"lon":-6.03415,"type":"city"},{"id":"ma-2557019","label":"Asni","lat":31.24653,"lon":-7.9789,"type":"city"},{"id":"ma-2556996","label":"Assa","lat":28.60986,"lon":-9.42986,"type":"city"},{"id":"ma-2556657","label":"Azemmour","lat":33.28952,"lon":-8.3425,"type":"city"},{"id":"ma-2556570","label":"Azilal","lat":31.96156,"lon":-6.57109,"type":"city"},{"id":"ma-2571932","label":"Azla","lat":35.55303,"lon":-5.24472,"type":"city"},{"id":"ma-2556464","label":"Azrou","lat":33.43443,"lon":-5.22126,"type":"city"},{"id":"ma-2556377","label":"Bab Taza","lat":35.06166,"lon":-5.19828,"type":"city"},{"id":"ma-12718663","label":"Bejaad","lat":32.77133,"lon":-6.39231,"type":"city"},{"id":"ma-10869575","label":"Bellaa","lat":30.05145,"lon":-9.56162,"type":"city"},{"id":"ma-2556076","label":"Ben Ahmed","lat":33.06635,"lon":-7.24161,"type":"city"},{"id":"ma-2556018","label":"Ben Guerir","lat":32.24088,"lon":-7.95397,"type":"city"},{"id":"ma-2555567","label":"Ben Jerrar","lat":30.26224,"lon":-9.50377,"type":"city"},{"id":"ma-2552975","label":"Ben Qarrich","lat":35.5109,"lon":-5.42047,"type":"city"},{"id":"ma-2555504","label":"Ben Taieb","lat":35.04427,"lon":-3.45418,"type":"city"},{"id":"ma-2555882","label":"Beni Enzar","lat":35.26,"lon":-2.93,"type":"city"},{"id":"ma-2555745","label":"Beni Mellal","lat":32.33725,"lon":-6.34983,"type":"city"},{"id":"ma-2558436","label":"Beni Yakhlef","lat":33.68407,"lon":-7.33924,"type":"city"},{"id":"ma-2555519","label":"Benslimane","lat":33.61601,"lon":-7.12153,"type":"city"},{"id":"ma-2555467","label":"Berkane","lat":34.92,"lon":-2.32,"type":"city"},{"id":"ma-2556272","label":"Berrechid","lat":33.26553,"lon":-7.58754,"type":"city"},{"id":"ma-2555395","label":"Bhalil","lat":33.85194,"lon":-4.87228,"type":"city"},{"id":"ma-2555342","label":"Bir Jdid","lat":33.37362,"lon":-7.99462,"type":"city"},{"id":"ma-10958491","label":"Bni Bouayach","lat":35.10506,"lon":-3.84028,"type":"city"},{"id":"ma-2555885","label":"Bni Drar","lat":34.86005,"lon":-1.98979,"type":"city"},{"id":"ma-2555610","label":"Bni Tajjit","lat":32.28928,"lon":-3.46616,"type":"city"},{"id":"ma-2554943","label":"Bou Fekrane","lat":33.76097,"lon":-5.48748,"type":"city"},{"id":"ma-2554594","label":"Bou Izakarn","lat":29.17705,"lon":-9.71181,"type":"city"},{"id":"ma-2555157","label":"Bouarfa","lat":32.53379,"lon":-1.96209,"type":"city"},{"id":"ma-2555009","label":"Boudenib","lat":31.95229,"lon":-3.60604,"type":"city"},{"id":"ma-11024543","label":"Bouderbala","lat":33.81672,"lon":-5.27583,"type":"city"},{"id":"ma-12718683","label":"Bouizazarene Ihaddadene","lat":35.15779,"lon":-2.97377,"type":"city"},{"id":"ma-6546693","label":"Boujniba","lat":32.90046,"lon":-6.77464,"type":"city"},{"id":"ma-2535530","label":"Bouknadel","lat":34.11849,"lon":-6.7389,"type":"city"},{"id":"ma-2554389","label":"Boulemane","lat":33.36376,"lon":-4.72896,"type":"city"},{"id":"ma-2554322","label":"Boumalne Dades","lat":31.37986,"lon":-5.98819,"type":"city"},{"id":"ma-2554281","label":"Boumia","lat":32.7236,"lon":-5.1025,"type":"city"},{"id":"ma-2554130","label":"Boureit","lat":34.99827,"lon":-4.89297,"type":"city"},{"id":"ma-2554006","label":"Bouskoura","lat":33.44976,"lon":-7.65239,"type":"city"},{"id":"ma-2553751","label":"Bouznika","lat":33.78942,"lon":-7.15968,"type":"city"},{"id":"ma-10955770","label":"Cap Negro II","lat":35.6597,"lon":-5.28525,"type":"city"},{"id":"ma-2553604","label":"Casablanca","lat":33.58831,"lon":-7.61138,"type":"city"},{"id":"ma-2553455","label":"Chefchaouen","lat":35.16878,"lon":-5.2636,"type":"city"},{"id":"ma-2553303","label":"Chichaoua","lat":31.54351,"lon":-8.76275,"type":"city"},{"id":"ma-8542188","label":"Dakhla","lat":30.41145,"lon":-9.55344,"type":"city"},{"id":"ma-2552615","label":"Dar Bouazza","lat":33.51535,"lon":-7.81677,"type":"city"},{"id":"ma-2552545","label":"Dar Ould Zidouh","lat":32.31247,"lon":-6.90494,"type":"city"},{"id":"ma-10374906","label":"Dchira El Jihadia","lat":30.37345,"lon":-9.54761,"type":"city"},{"id":"ma-2552407","label":"Debdou","lat":33.98228,"lon":-3.04263,"type":"city"},{"id":"ma-2552317","label":"Demnate","lat":31.73443,"lon":-7.00505,"type":"city"},{"id":"ma-2531453","label":"Dhar Souk","lat":34.65197,"lon":-4.27921,"type":"city"},{"id":"ma-2551836","label":"Douar el Caid el Gueddari","lat":34.42121,"lon":-6.09099,"type":"city"},{"id":"ma-2551147","label":"Douar Toulal","lat":33.88483,"lon":-5.59664,"type":"city"},{"id":"ma-2550985","label":"Driouch","lat":34.97705,"lon":-3.37902,"type":"city"},{"id":"ma-2553382","label":"Echemmaia Est","lat":32.08102,"lon":-8.62458,"type":"city"},{"id":"ma-2550806","label":"El Aioun","lat":34.58319,"lon":-2.50612,"type":"city"},{"id":"ma-2550419","label":"El Gara","lat":33.27732,"lon":-7.23236,"type":"city"},{"id":"ma-12718690","label":"El Guerdane","lat":30.37757,"lon":-9.01997,"type":"city"},{"id":"ma-2550252","label":"El Hajeb","lat":33.68786,"lon":-5.371,"type":"city"},{"id":"ma-2550162","label":"El Harhoura","lat":33.94483,"lon":-6.93106,"type":"city"},{"id":"ma-2550078","label":"El Jadida","lat":33.25682,"lon":-8.50882,"type":"city"},{"id":"ma-2549979","label":"El Kelaa des Srarhna","lat":32.05121,"lon":-7.41079,"type":"city"},{"id":"ma-2549750","label":"El Ksiba","lat":32.57286,"lon":-6.01947,"type":"city"},{"id":"ma-2558428","label":"El Mansouria","lat":33.74643,"lon":-7.30194,"type":"city"},{"id":"ma-2549623","label":"El Menzel","lat":33.83758,"lon":-4.54472,"type":"city"},{"id":"ma-12718678","label":"El Ouatia","lat":28.49624,"lon":-11.33268,"type":"city"},{"id":"ma-7280528","label":"Errachidia","lat":31.9314,"lon":-4.42663,"type":"city"},{"id":"ma-2549263","label":"Essaouira","lat":31.5125,"lon":-9.77,"type":"city"},{"id":"ma-12718689","label":"Fam El Hisn","lat":29.01889,"lon":-8.89111,"type":"city"},{"id":"ma-2548885","label":"Fes","lat":34.03313,"lon":-5.00028,"type":"city"},{"id":"ma-2548880","label":"Fes al Bali","lat":34.0701,"lon":-4.95473,"type":"city"},{"id":"ma-2548851","label":"Figuig","lat":32.10891,"lon":-1.22855,"type":"city"},{"id":"ma-2548818","label":"Fnidek","lat":35.84906,"lon":-5.35747,"type":"city"},{"id":"ma-2532440","label":"Foum Jam'a","lat":31.96166,"lon":-6.98354,"type":"city"},{"id":"ma-2548769","label":"Foum Zguid","lat":30.08792,"lon":-6.87119,"type":"city"},{"id":"ma-2548676","label":"Ghafsai","lat":34.62799,"lon":-4.91266,"type":"city"},{"id":"ma-2548623","label":"Goulmima","lat":31.69227,"lon":-4.95256,"type":"city"},{"id":"ma-2548601","label":"Gourrama","lat":32.34016,"lon":-4.07349,"type":"city"},{"id":"ma-2548526","label":"Guelmim","lat":28.98696,"lon":-10.05738,"type":"city"},{"id":"ma-9645313","label":"Gueltat Zemmour","lat":25.14276,"lon":-12.37168,"type":"city"},{"id":"ma-2548489","label":"Guercif","lat":34.22568,"lon":-3.35361,"type":"city"},{"id":"ma-2537368","label":"Gueznaia","lat":35.70211,"lon":-5.89044,"type":"city"},{"id":"ma-2548320","label":"Had Kourt","lat":34.61588,"lon":-5.7404,"type":"city"},{"id":"ma-10933159","label":"Had Oulad Zbair","lat":34.2894,"lon":-4.31952,"type":"city"},{"id":"ma-12718675","label":"Had Soualem","lat":33.41972,"lon":-7.85237,"type":"city"},{"id":"ma-2548196","label":"Haj Kaddour","lat":33.82507,"lon":-5.42501,"type":"city"},{"id":"ma-12718662","label":"Hattane","lat":32.84085,"lon":-6.80027,"type":"city"},{"id":"ma-2543394","label":"Ifrane","lat":31.70217,"lon":-6.3494,"type":"city"},{"id":"ma-2546917","label":"Ifrane","lat":33.52666,"lon":-5.11019,"type":"city"},{"id":"ma-12718660","label":"Ighram Laalam","lat":32.52378,"lon":-6.14977,"type":"city"},{"id":"ma-2546128","label":"Imi-n-Tanout","lat":31.17213,"lon":-8.84728,"type":"city"},{"id":"ma-2546028","label":"Imouzzer Kandar","lat":33.72871,"lon":-5.01092,"type":"city"},{"id":"ma-2550898","label":"Imzouren","lat":35.14637,"lon":-3.85063,"type":"city"},{"id":"ma-2545957","label":"Inezgane","lat":30.35535,"lon":-9.53639,"type":"city"},{"id":"ma-2545346","label":"Itzer","lat":32.8783,"lon":-5.0515,"type":"city"},{"id":"ma-2545051","label":"Jamaat Shaim","lat":32.34694,"lon":-8.84249,"type":"city"},{"id":"ma-2532420","label":"Jem'at Oulad 'Abbou","lat":33.1148,"lon":-7.9336,"type":"city"},{"id":"ma-2545017","label":"Jerada","lat":34.31,"lon":-2.16,"type":"city"},{"id":"ma-2544968","label":"Jorf","lat":31.49442,"lon":-4.40598,"type":"city"},{"id":"ma-12718659","label":"Kahf Nssar","lat":32.91361,"lon":-5.95873,"type":"city"},{"id":"ma-2544821","label":"Karia Ba Mohamed","lat":34.37094,"lon":-5.2138,"type":"city"},{"id":"ma-2544815","label":"Kariat Arkmane","lat":35.1071,"lon":-2.74693,"type":"city"},{"id":"ma-2544720","label":"Kasba Tadla","lat":32.5977,"lon":-6.26844,"type":"city"},{"id":"ma-2549981","label":"Kelaat Mgouna","lat":31.24573,"lon":-6.1326,"type":"city"},{"id":"ma-2544571","label":"Kenitra","lat":34.26101,"lon":-6.5802,"type":"city"},{"id":"ma-2544367","label":"Khemis Sahel","lat":35.25344,"lon":-6.0796,"type":"city"},{"id":"ma-2558470","label":"Khemisset","lat":33.82404,"lon":-6.06627,"type":"city"},{"id":"ma-2544334","label":"Khenichet-sur Ouerrha","lat":34.44041,"lon":-5.67879,"type":"city"},{"id":"ma-2544333","label":"Khenifra","lat":32.93492,"lon":-5.66167,"type":"city"},{"id":"ma-2544248","label":"Khouribga","lat":32.88108,"lon":-6.9063,"type":"city"},{"id":"ma-2544001","label":"Ksar El Kebir","lat":35.00044,"lon":-5.90378,"type":"city"},{"id":"ma-12718681","label":"Laattaouia","lat":31.83532,"lon":-7.31431,"type":"city"},{"id":"ma-12718676","label":"Lahraouyine","lat":33.54138,"lon":-7.52848,"type":"city"},{"id":"ma-12718677","label":"Lakhsas","lat":29.36606,"lon":-9.75082,"type":"city"},{"id":"ma-2543667","label":"Lalla Mimouna","lat":34.84606,"lon":-6.06645,"type":"city"},{"id":"ma-2550749","label":"Laouamra","lat":35.06938,"lon":-6.08835,"type":"city"},{"id":"ma-2543549","label":"Larache","lat":35.19321,"lon":-6.15572,"type":"city"},{"id":"ma-11025160","label":"Lemhaya","lat":33.97716,"lon":-5.251,"type":"city"},{"id":"ma-10904142","label":"Loudaya","lat":31.63348,"lon":-8.24893,"type":"city"},{"id":"ma-10375044","label":"Lqoliaa","lat":30.29759,"lon":-9.46597,"type":"city"},{"id":"ma-2542997","label":"Marrakesh","lat":31.63416,"lon":-7.99994,"type":"city"},{"id":"ma-2542987","label":"Martil","lat":35.61662,"lon":-5.27522,"type":"city"},{"id":"ma-2542898","label":"Mdiq","lat":35.68313,"lon":-5.32871,"type":"city"},{"id":"ma-12718680","label":"Mechouar-Kasba","lat":31.6008,"lon":-7.98653,"type":"city"},{"id":"ma-2542866","label":"Mechraa Bel Ksiri","lat":34.57373,"lon":-5.95585,"type":"city"},{"id":"ma-2542826","label":"Mediouna","lat":33.45161,"lon":-7.51995,"type":"city"},{"id":"ma-2542768","label":"Mehdya","lat":34.25596,"lon":-6.67345,"type":"city"},{"id":"ma-2542715","label":"Meknes","lat":33.89352,"lon":-5.54727,"type":"city"},{"id":"ma-2542616","label":"Melqa el Ouidane","lat":34.55964,"lon":-3.02321,"type":"city"},{"id":"ma-12718686","label":"Mers El Kheir","lat":33.86262,"lon":-6.92964,"type":"city"},{"id":"ma-2565267","label":"Mhamid","lat":29.82,"lon":-5.72,"type":"city"},{"id":"ma-2542230","label":"Midar","lat":34.94025,"lon":-3.53311,"type":"city"},{"id":"ma-2542227","label":"Midelt","lat":32.6852,"lon":-4.74512,"type":"city"},{"id":"ma-2542167","label":"Mirleft","lat":29.57829,"lon":-10.03245,"type":"city"},{"id":"ma-2542147","label":"Missour","lat":33.04893,"lon":-3.98947,"type":"city"},{"id":"ma-2542051","label":"Mohammedia","lat":33.68607,"lon":-7.38298,"type":"city"},{"id":"ma-2541906","label":"Moulay Abdallah","lat":33.19664,"lon":-8.58811,"type":"city"},{"id":"ma-12718664","label":"Moulay Ali Cherif","lat":31.28244,"lon":-4.26541,"type":"city"},{"id":"ma-2541843","label":"Moulay Bou 'azza","lat":33.22576,"lon":-6.19807,"type":"city"},{"id":"ma-2541833","label":"Moulay Bousselham","lat":34.88158,"lon":-6.29455,"type":"city"},{"id":"ma-2541805","label":"Moulay Driss Zerhoun","lat":34.05555,"lon":-5.52132,"type":"city"},{"id":"ma-2541779","label":"Moulay Yacoub","lat":34.08793,"lon":-5.18171,"type":"city"},{"id":"ma-2545069","label":"Mrirt","lat":33.16427,"lon":-5.56722,"type":"city"},{"id":"ma-10375207","label":"My Drarga","lat":30.37733,"lon":-9.47342,"type":"city"},{"id":"ma-2541479","label":"Nador","lat":35.16813,"lon":-2.93352,"type":"city"},{"id":"ma-2548878","label":"New Fes","lat":34.05466,"lon":-5.00725,"type":"city"},{"id":"ma-10375138","label":"Oadar Temsia","lat":30.36531,"lon":-9.41044,"type":"city"},{"id":"ma-2541068","label":"Oualidia","lat":32.73372,"lon":-9.03059,"type":"city"},{"id":"ma-12718661","label":"Ouaouizeght","lat":32.15872,"lon":-6.35408,"type":"city"},{"id":"ma-2540850","label":"Ouarzazate","lat":30.91894,"lon":-6.89341,"type":"city"},{"id":"ma-2540716","label":"Oued Amlil","lat":34.2,"lon":-4.28,"type":"city"},{"id":"ma-2540698","label":"Oued Laou","lat":35.4484,"lon":-5.09627,"type":"city"},{"id":"ma-2540689","label":"Oued Zem","lat":32.8627,"lon":-6.57359,"type":"city"},{"id":"ma-2540810","label":"Ouezzane","lat":34.79584,"lon":-5.57849,"type":"city"},{"id":"ma-12718669","label":"Ouislane","lat":33.91406,"lon":-5.48969,"type":"city"},{"id":"ma-2540483","label":"Oujda","lat":34.68139,"lon":-1.90858,"type":"city"},{"id":"ma-2540207","label":"Oulad Ayad","lat":32.2,"lon":-6.8,"type":"city"},{"id":"ma-2540180","label":"Oulad Barhil","lat":30.64042,"lon":-8.46875,"type":"city"},{"id":"ma-11471726","label":"Oulad El Rhadabne","lat":33.17521,"lon":-8.60592,"type":"city"},{"id":"ma-2539829","label":"Oulad Embarek","lat":32.27162,"lon":-6.44967,"type":"city"},{"id":"ma-2548343","label":"Oulad Frej","lat":32.95956,"lon":-8.2274,"type":"city"},{"id":"ma-12718674","label":"Oulad M'Rah","lat":32.91284,"lon":-7.26438,"type":"city"},{"id":"ma-2539139","label":"Oulad Tayeb","lat":33.94633,"lon":-4.99509,"type":"city"},{"id":"ma-2539134","label":"Oulad Teima","lat":30.39467,"lon":-9.20897,"type":"city"},{"id":"ma-2539114","label":"Oulad Yaich","lat":32.43498,"lon":-6.3245,"type":"city"},{"id":"ma-2538898","label":"Oulmes","lat":33.42585,"lon":-6.00137,"type":"city"},{"id":"ma-2538573","label":"Outat Oulad Al Haj","lat":33.34499,"lon":-3.70387,"type":"city"},{"id":"ma-2538475","label":"Rabat","lat":34.01325,"lon":-6.83255,"type":"city"},{"id":"ma-2538401","label":"Ras el Ma","lat":33.97399,"lon":-5.09613,"type":"city"},{"id":"ma-2538392","label":"Ras Kebdana","lat":35.14069,"lon":-2.42455,"type":"city"},{"id":"ma-2538027","label":"Recani","lat":31.28318,"lon":-4.26565,"type":"city"},{"id":"ma-2596460","label":"Ribat Al Khayr","lat":33.81518,"lon":-4.40717,"type":"city"},{"id":"ma-2538059","label":"Rich","lat":32.25644,"lon":-4.50152,"type":"city"},{"id":"ma-11025266","label":"Sabaa Aiyoun","lat":33.90331,"lon":-5.36868,"type":"city"},{"id":"ma-2537881","label":"Safi","lat":32.29939,"lon":-9.23718,"type":"city"},{"id":"ma-2537802","label":"Saidia","lat":35.08195,"lon":-2.22897,"type":"city"},{"id":"ma-2537763","label":"Sale","lat":34.0531,"lon":-6.79846,"type":"city"},{"id":"ma-10920963","label":"Sale Al Jadida","lat":33.99722,"lon":-6.74047,"type":"city"},{"id":"ma-2537611","label":"Sebt Bni Garfett","lat":35.25796,"lon":-5.83334,"type":"city"},{"id":"ma-2537610","label":"Sebt Gzoula","lat":32.10779,"lon":-9.08366,"type":"city"},{"id":"ma-2537545","label":"Sefrou","lat":33.83186,"lon":-4.828,"type":"city"},{"id":"ma-2537469","label":"Selouane","lat":35.07313,"lon":-2.9423,"type":"city"},{"id":"ma-2537406","label":"Settat","lat":33.00103,"lon":-7.61662,"type":"city"},{"id":"ma-2526239","label":"Setti Fatma","lat":31.22508,"lon":-7.67751,"type":"city"},{"id":"ma-10640347","label":"Sidi Ahmed","lat":32.20807,"lon":-8.49141,"type":"city"},{"id":"ma-12718673","label":"Sidi Ali Ben Hamdouche","lat":33.28665,"lon":-8.32664,"type":"city"},{"id":"ma-2536392","label":"Sidi Allal El Bahraoui","lat":34.0077,"lon":-6.53082,"type":"city"},{"id":"ma-2536383","label":"Sidi Allal Tazi","lat":34.52257,"lon":-6.32197,"type":"city"},{"id":"ma-2536074","label":"Sidi Bennour","lat":32.65236,"lon":-8.42769,"type":"city"},{"id":"ma-2536047","label":"Sidi Bibi","lat":30.23784,"lon":-9.52877,"type":"city"},{"id":"ma-2535619","label":"Sidi Bou Lanouar","lat":32.86,"lon":-6.88,"type":"city"},{"id":"ma-2535534","label":"Sidi Bou Othmane","lat":31.90226,"lon":-7.94169,"type":"city"},{"id":"ma-8556357","label":"Sidi Bouzid","lat":33.23151,"lon":-8.55062,"type":"city"},{"id":"ma-2534515","label":"Sidi Ifni","lat":29.37975,"lon":-10.17299,"type":"city"},{"id":"ma-2534496","label":"Sidi Jaber","lat":32.38952,"lon":-6.42095,"type":"city"},{"id":"ma-2533191","label":"Sidi Kacem","lat":34.22149,"lon":-5.70775,"type":"city"},{"id":"ma-2533481","label":"Sidi Lmokhtar","lat":31.57739,"lon":-9.01575,"type":"city"},{"id":"ma-2533182","label":"Sidi Rahal","lat":33.47739,"lon":-7.93641,"type":"city"},{"id":"ma-2533178","label":"Sidi Rahhal","lat":31.65031,"lon":-7.47288,"type":"city"},{"id":"ma-2532945","label":"Sidi Slimane","lat":34.26479,"lon":-5.92598,"type":"city"},{"id":"ma-12718684","label":"Sidi Slimane Echcharaa","lat":34.90818,"lon":-2.35055,"type":"city"},{"id":"ma-2532918","label":"Sidi Smai'il","lat":32.82461,"lon":-8.51122,"type":"city"},{"id":"ma-10797349","label":"Sidi Taibi","lat":34.18698,"lon":-6.68176,"type":"city"},{"id":"ma-2532822","label":"Sidi Yahia El Gharb","lat":34.30494,"lon":-6.30404,"type":"city"},{"id":"ma-2532821","label":"Sidi Yahya Zaer","lat":33.82977,"lon":-6.91262,"type":"city"},{"id":"ma-2532707","label":"Sidi Zouine","lat":31.66914,"lon":-8.34541,"type":"city"},{"id":"ma-2562055","label":"Skhirate","lat":33.8527,"lon":-7.03171,"type":"city"},{"id":"ma-2532646","label":"Skhour Rehamna","lat":32.48244,"lon":-7.91533,"type":"city"},{"id":"ma-2461874","label":"Smara","lat":26.73841,"lon":-11.67194,"type":"city"},{"id":"ma-11131249","label":"Souk El Arba Des Ait Baha","lat":30.06958,"lon":-9.15465,"type":"city"},{"id":"ma-12718688","label":"Souk El Arbaa","lat":34.68473,"lon":-6.00344,"type":"city"},{"id":"ma-2532421","label":"Souk et Tnine Jorf el Mellah","lat":34.49162,"lon":-5.50846,"type":"city"},{"id":"ma-2532434","label":"Souq Al Had Bradya","lat":32.44928,"lon":-6.5366,"type":"city"},{"id":"ma-2532405","label":"Souq at Tlata des Loulad","lat":32.99471,"lon":-7.11982,"type":"city"},{"id":"ma-10965229","label":"Souq Khmis Ait Yadine","lat":33.9716,"lon":-6.01689,"type":"city"},{"id":"ma-2532394","label":"Souq Larb'a al Gharb","lat":34.68664,"lon":-6.00272,"type":"city"},{"id":"ma-2532412","label":"Souq Sebt Oulad Nemma","lat":32.2973,"lon":-6.70301,"type":"city"},{"id":"ma-2532171","label":"Tabount","lat":30.90321,"lon":-6.91579,"type":"city"},{"id":"ma-2531877","label":"Tafraout","lat":29.72449,"lon":-8.9747,"type":"city"},{"id":"ma-2568012","label":"Taghazout","lat":30.54259,"lon":-9.71115,"type":"city"},{"id":"ma-2531432","label":"Tahannout","lat":31.35236,"lon":-7.95012,"type":"city"},{"id":"ma-2531480","label":"Tahla","lat":34.04965,"lon":-4.42162,"type":"city"},{"id":"ma-2531171","label":"Talat-n-Ya'qoub","lat":30.98893,"lon":-8.18927,"type":"city"},{"id":"ma-2531014","label":"Taliouine","lat":30.52917,"lon":-7.91262,"type":"city"},{"id":"ma-2530923","label":"Talsint","lat":32.53599,"lon":-3.44143,"type":"city"},{"id":"ma-2530704","label":"Tamallalt","lat":31.81897,"lon":-7.51446,"type":"city"},{"id":"ma-2530843","label":"Tamanar","lat":31.00087,"lon":-9.67802,"type":"city"},{"id":"ma-8504943","label":"Tamansourt","lat":31.755,"lon":-8.11,"type":"city"},{"id":"ma-2530641","label":"Tameslouht","lat":31.49472,"lon":-8.09772,"type":"city"},{"id":"ma-8299790","label":"Tamesna","lat":33.81809,"lon":-6.91658,"type":"city"},{"id":"ma-2530241","label":"Tan-Tan","lat":28.43799,"lon":-11.10321,"type":"city"},{"id":"ma-2530335","label":"Tangier","lat":35.76727,"lon":-5.79975,"type":"city"},{"id":"ma-2530155","label":"Taounate","lat":34.53661,"lon":-4.64009,"type":"city"},{"id":"ma-2530048","label":"Taourirt","lat":34.40731,"lon":-2.89732,"type":"city"},{"id":"ma-2529923","label":"Tarfaya","lat":27.9392,"lon":-12.92604,"type":"city"},{"id":"ma-2529872","label":"Targuist","lat":34.93769,"lon":-4.31856,"type":"city"},{"id":"ma-2529777","label":"Tarhjicht","lat":29.05827,"lon":-9.42877,"type":"city"},{"id":"ma-2529649","label":"Taroudant","lat":30.47028,"lon":-8.87695,"type":"city"},{"id":"ma-2529411","label":"Tassila","lat":29.97134,"lon":-9.64195,"type":"city"},{"id":"ma-2529362","label":"Tata","lat":29.74409,"lon":-7.973,"type":"city"},{"id":"ma-2529317","label":"Taza","lat":34.21,"lon":-4.01,"type":"city"},{"id":"ma-2529245","label":"Taznakht","lat":30.57836,"lon":-7.20341,"type":"city"},{"id":"ma-2529013","label":"Temara","lat":33.92866,"lon":-6.90656,"type":"city"},{"id":"ma-2528981","label":"Tendrara","lat":33.04964,"lon":-2.00018,"type":"city"},{"id":"ma-2528910","label":"Tetouan","lat":35.57845,"lon":-5.36837,"type":"city"},{"id":"ma-2528659","label":"Tiflet","lat":33.89469,"lon":-6.30649,"type":"city"},{"id":"ma-2527925","label":"Tinajdad","lat":31.50764,"lon":-5.03293,"type":"city"},{"id":"ma-10374981","label":"Tine Biougra","lat":30.20942,"lon":-9.37922,"type":"city"},{"id":"ma-2527915","label":"Tinghir","lat":31.51472,"lon":-5.53278,"type":"city"},{"id":"ma-2527645","label":"Tirhanimine","lat":35.23619,"lon":-3.95453,"type":"city"},{"id":"ma-2527641","label":"Tirhassaline","lat":32.7822,"lon":-5.65282,"type":"city"},{"id":"ma-2527366","label":"Tissa","lat":34.28791,"lon":-4.66372,"type":"city"},{"id":"ma-2527271","label":"Tit Mellil","lat":33.55808,"lon":-7.48647,"type":"city"},{"id":"ma-2527089","label":"Tiznit","lat":29.69742,"lon":-9.73162,"type":"city"},{"id":"ma-2527055","label":"Tiztoutine","lat":34.97159,"lon":-3.15273,"type":"city"},{"id":"ma-2549150","label":"Tlet El Hanchane","lat":31.52207,"lon":-9.43594,"type":"city"},{"id":"ma-2526710","label":"Tounfit","lat":32.46945,"lon":-5.24512,"type":"city"},{"id":"ma-2526488","label":"Youssoufia","lat":32.24634,"lon":-8.52941,"type":"city"},{"id":"ma-2526459","label":"Zag","lat":28.0221,"lon":-9.29397,"type":"city"},{"id":"ma-2526452","label":"Zagora","lat":30.33241,"lon":-5.8384,"type":"city"},{"id":"ma-2526435","label":"Zaio","lat":34.94282,"lon":-2.7329,"type":"city"},{"id":"ma-2526389","label":"Zaouia Ait Ishak","lat":32.76181,"lon":-5.72535,"type":"city"},{"id":"ma-2541210","label":"Zawyat an Nwacer","lat":33.37981,"lon":-7.61932,"type":"city"},{"id":"ma-2526359","label":"Zawyat ech Cheikh","lat":32.64445,"lon":-5.91826,"type":"city"},{"id":"ma-2526104","label":"Zayda","lat":32.81921,"lon":-4.96099,"type":"city"},{"id":"ma-2537538","label":"Zeghanghane","lat":35.15561,"lon":-3.00236,"type":"city"},{"id":"ma-2549888","label":"Zemamra","lat":32.62287,"lon":-8.70227,"type":"city"},{"id":"ma-12718685","label":"Zirara","lat":34.24099,"lon":-5.7424,"type":"city"},{"id":"ma-12718668","label":"Zoualet","lat":33.93664,"lon":-5.46514,"type":"city"}]